sphinxcontrib_commandoutput-0.17.11-py3.8-nspkg.pth
sphinxcontrib/commandoutput/__init__.py
sphinxcontrib/commandoutput/tests/__init__.py
sphinxcontrib/commandoutput/tests/test_cache.py
sphinxcontrib/commandoutput/tests/test_command.py
sphinxcontrib/commandoutput/tests/test_directive.py
sphinxcontrib/commandoutput/tests/test_setup.py
sphinxcontrib/commandoutput/tests/test_util.py
sphinxcontrib_commandoutput-0.17.11.dist-info/LICENSE
sphinxcontrib_commandoutput-0.17.11.dist-info/METADATA
sphinxcontrib_commandoutput-0.17.11.dist-info/WHEEL
sphinxcontrib_commandoutput-0.17.11.dist-info/namespace_packages.txt
sphinxcontrib_commandoutput-0.17.11.dist-info/top_level.txt
sphinxcontrib_commandoutput-0.17.11.dist-info/RECORD
