Metadata-Version: 2.1
Name: sphinxcontrib-commandoutput
Version: 0.17.11
Summary: Sphinx extension to include command output
Home-page: UNKNOWN
Author: Sebastian Wiesner
Author-email: lunaryorn@gmail.com
Maintainer: Raphaël Dias--Monteiro
Maintainer-email: raphael.diasmonteiro@outlook.fr
License: BSD
Keywords: sphinx cli command output program example
Platform: any
Classifier: Development Status :: 5 - Production/Stable
Classifier: Intended Audience :: Developers
Classifier: License :: OSI Approved :: BSD License
Classifier: Operating System :: OS Independent
Classifier: Programming Language :: Python
Classifier: Programming Language :: Python :: 2
Classifier: Programming Language :: Python :: 3
Classifier: Programming Language :: Python :: 2.7
Classifier: Programming Language :: Python :: 3.5
Classifier: Programming Language :: Python :: 3.6
Classifier: Programming Language :: Python :: 3.7
Classifier: Programming Language :: Python :: Implementation :: CPython
Classifier: Programming Language :: Python :: Implementation :: PyPy
Classifier: Topic :: Documentation
Classifier: Topic :: Utilities
Classifier: Framework :: Sphinx
Classifier: Framework :: Sphinx :: Extension
Requires-Python: >=2.7,!=3.0.*,!=3.1.*,!=3.2.*,!=3.3.*,!=3.4.*
Requires-Dist: Sphinx (>=1.7.0)
Provides-Extra: test
